csv_to_xlsx_report/__init__.py
csv_to_xlsx_report/csv_to_xlsx_report.py
csv_to_xlsx_report-0.0.4.dist-info/METADATA
csv_to_xlsx_report-0.0.4.dist-info/WHEEL
csv_to_xlsx_report-0.0.4.dist-info/licenses/LICENSE
csv_to_xlsx_report-0.0.4.dist-info/RECORD
