Metadata-Version: 2.4
Name: csv_to_xlsx_report
Version: 0.0.4
Summary: Modularized conversion of a csv file into a presentable executive spreadsheet.
Project-URL: Homepage, https://github.com/fisherm7/csv_to_xlsx_report
License-Expression: MIT
License-File: LICENSE
Keywords: csv,excel,xlsx
Classifier: Operating System :: OS Independent
Classifier: Programming Language :: Python :: 3
Requires-Python: >=3.7
Requires-Dist: pandas>=2.2.3
Requires-Dist: xlsxwriter>=3.2.3
